[{
	"icon": "fa fa-th-list",
	"title": "Validate",
	"subMenus": [
		{
			"title": "Validate Demo",
			"href": "/Example/lib/validate/index.html"
		}
	]
},{
	"icon": "fa fa-th-list",
	"title": "Canvas Exercise",
	"subMenus": [
		{
			"title": "Canvas Demo1",
			"href": "/Example/pages/Canvas/canvas1.html"
		},{
			"title": "Canvas Demo2",
			"href": "/Example/pages/Canvas/canvas2.html"
		},{
			"title": "Canvas Demo3",
			"href": "/Example/pages/Canvas/canvas3/canvas3.html"
		},{
			"title": "Canvas Demo4",
			"href": "/Example/pages/Canvas/canvas4.html"
		}
	]
},{
	"icon": "fa fa-th-list",
	"title": "Backbone Demo",
	"subMenus": [
		{
			"title": "TodoMVC",
			"href": "/Example/pages/TodoMVC/index.html"
		}
	]
},{
	"icon": "fa fa-th-list",
	"title": "Circle Hover Effects",
	"subMenus": [
		{
			"title": "Demos",
			"href": "/Example/pages/CircleHoverEffects/index.html"
		}
	]
},{
	"icon": "fa fa-th-list",
	"title": "3D Hover Effects",
	"subMenus": [
		{
			"title": "Demos",
			"href": "/Example/pages/3DHoverEffects/index.html"
		}
	]
},{
	"icon": "fa fa-th-list",
	"title": "3D Image Slider",
	"subMenus": [
		{
			"title": "3D image slider",
			"href": "/Example/pages/css-3D-image-slider/index-amd.html"
		}
	]
},{
	"icon": "fa fa-th-list",
	"title": "Animate.css",
	"subMenus": [
		{
			"title": "Animate.css 效果示例",
			"href": "https://daneden.github.io/animate.css/"
		}
	]
},{
	"icon": "fa fa-th-list",
	"title": "图片剪裁",
	"subMenus": [
		{
			"title": "图片剪裁 demos",
			"href": "http://deepliquid.com/projects/Jcrop/demos.php"
		}
	]
}]